langflow_client/__init__.py
langflow_client/client.py
langflow_client/consts.py
langflow_client/errors.py
langflow_client/files.py
langflow_client/flow.py
langflow_client/flow_response.py
langflow_client/log.py
langflow_client/logs.py
langflow_client/ndjson.py
langflow_client/types.py
langflow_client/upload_response.py
langflow_client/user_file.py
langflow_client-0.1.0.dist-info/licenses/LICENSE
langflow_client-0.1.0.dist-info/METADATA
langflow_client-0.1.0.dist-info/WHEEL
langflow_client-0.1.0.dist-info/top_level.txt
langflow_client-0.1.0.dist-info/RECORD
