Metadata-Version: 2.4
Name: langflow-client
Version: 0.1.0
Summary: Un-official Python client for the Langflow API
Author: Ilya Melnikov
License:                                  Apache License
Project-URL: Homepage, https://github.com/aisurfer/langflow-client-python
Project-URL: Issues, https://github.com/aisurfer/langflow-client-python/issues
Keywords: langflow,llm,ai,client
Classifier: License :: OSI Approved :: Apache Software License
Classifier: Programming Language :: Python :: 3
Classifier: Programming Language :: Python :: 3 :: Only
Classifier: Programming Language :: Python :: 3.9
Classifier: Programming Language :: Python :: 3.10
Classifier: Programming Language :: Python :: 3.11
Classifier: Programming Language :: Python :: 3.12
Classifier: Topic :: Software Development :: Libraries
Requires-Python: >=3.9
License-File: LICENSE
Requires-Dist: requests>=2.28.0
Requires-Dist: typing-extensions>=4.5.0; python_version < "3.10"
Provides-Extra: test
Requires-Dist: pytest>=7.0; extra == "test"
Requires-Dist: pytest-asyncio>=1.1.0; extra == "test"
Requires-Dist: python-dotenv>=1.0.0; extra == "test"
Dynamic: license-file
